hipposhic/__init__.py
hipposhic/file1.py
hipposhic/file2.py
hipposhic-0.1.3.data/scripts/exampleScript
hipposhic-0.1.3.dist-info/LICENCE
hipposhic-0.1.3.dist-info/METADATA
hipposhic-0.1.3.dist-info/WHEEL
hipposhic-0.1.3.dist-info/top_level.txt
hipposhic-0.1.3.dist-info/RECORD
