Metadata-Version: 2.1
Name: hipposhic
Version: 0.1.3
Summary: my first upload to pyPI
Home-page: https://github.com/jgallowa07/hipposhic.git
Author: Jared Galloway
Author-email: jaredgalloway07@gmail.com
License: MIT
Platform: UNKNOWN
Requires-Dist: numpy
Provides-Extra: dev
